<?xml version="1.0" encoding="utf-8"?>
<Messages>
	<Message severity="INFO" prefix="[SCHED 204-61]" key="SCHED_PIPELINING_STATUS_631" tag="SCHEDULE" content="Option &apos;relax_ii_for_timing&apos; is enabled, will increase II to preserve clock frequency constraints."/>
	<Message severity="INFO" prefix="[HLS 200-10]" key="HLS_10_1312" tag="" content="Analyzing design file &apos;matvec.cpp&apos; ..."/>
	<Message severity="WARNING" prefix="[HLS 214-111]" key="HLS 214-111" tag="DATAFLOW,SDX_KERNEL" content="Static scalars and arrays declared inside a dataflow region will be treated like local variables: matvec.cpp:6:15"/>
	<Message severity="WARNING" prefix="[HLS 214-111]" key="HLS 214-111" tag="DATAFLOW,SDX_KERNEL" content="Static scalars and arrays declared inside a dataflow region will be treated like local variables: matvec.cpp:16:15"/>
	<Message severity="WARNING" prefix="[HLS 214-114]" key="HLS 214-114" tag="DATAFLOW,SDX_KERNEL" content="Since the only kind of statements allowed in a canonical dataflow region are variable declarations and function calls, the compiler may not be able to correctly handle the region: matvec.cpp:8:2"/>
	<Message severity="WARNING" prefix="[HLS 214-114]" key="HLS 214-114" tag="DATAFLOW,SDX_KERNEL" content="Since the only kind of statements allowed in a canonical dataflow region are variable declarations and function calls, the compiler may not be able to correctly handle the region: matvec.cpp:17:2"/>
	<Message severity="WARNING" prefix="[HLS 214-114]" key="HLS 214-114" tag="DATAFLOW,SDX_KERNEL" content="Since the only kind of statements allowed in a canonical dataflow region are variable declarations and function calls, the compiler may not be able to correctly handle the region: matvec.cpp:26:2"/>
	<Message severity="WARNING" prefix="[HLS 214-167]" key="HLS 214-167" tag="DATAFLOW,SDX_KERNEL" content="There are a total of 4 such instances of non-canonical statements in the dataflow region: matvec.cpp:6:2"/>
	<Message severity="WARNING" prefix="[HLS 200-471]" key="HLS 200-471" tag="DATAFLOW,SDX_KERNEL" content="Dataflow form checks found 6 issue(s) in file matvec.cpp"/>
	<Message severity="INFO" prefix="[HLS 200-111]" key="HLS_111_965" tag="" content="Finished Linking Time (s): cpu = 00:00:09 ; elapsed = 00:00:10 . Memory (MB): peak = 898.758 ; gain = 459.035 ; free physical = 202 ; free virtual = 2836"/>
	<Message severity="INFO" prefix="[HLS 200-111]" key="HLS_111_965" tag="" content="Finished Checking Pragmas Time (s): cpu = 00:00:09 ; elapsed = 00:00:10 . Memory (MB): peak = 898.758 ; gain = 459.035 ; free physical = 202 ; free virtual = 2836"/>
	<Message severity="INFO" prefix="[HLS 200-10]" key="HLS_10_1467" tag="" content="Starting code transformations ..."/>
	<Message severity="INFO" prefix="[HLS 200-111]" key="HLS_111_965" tag="" content="Finished Standard Transforms Time (s): cpu = 00:00:10 ; elapsed = 00:00:11 . Memory (MB): peak = 898.758 ; gain = 459.035 ; free physical = 198 ; free virtual = 2833"/>
	<Message severity="INFO" prefix="[HLS 200-10]" key="HLS_10_1472" tag="" content="Checking synthesizability ..."/>
	<Message severity="INFO" prefix="[HLS 200-111]" key="HLS_111_965" tag="" content="Finished Checking Synthesizability Time (s): cpu = 00:00:10 ; elapsed = 00:00:11 . Memory (MB): peak = 898.758 ; gain = 459.035 ; free physical = 195 ; free virtual = 2831"/>
	<Message severity="INFO" prefix="[XFORM 203-102]" key="XFORM_AUTO_PARTITION_STATUS_112" tag="" content="Automatically partitioning streamed array &apos;Atile.V.vec&apos; (matvec.cpp:3) ."/>
	<Message severity="INFO" prefix="[XFORM 203-102]" key="XFORM_AUTO_PARTITION_STATUS_112" tag="" content="Automatically partitioning streamed array &apos;xtile.V.vec&apos; (matvec.cpp:3) ."/>
	<Message severity="INFO" prefix="[XFORM 203-101]" key="XFORM_PARTITION_STATUS_116" tag="" content="Partitioning array &apos;Atile.V.vec&apos; (matvec.cpp:3) in dimension 1 completely."/>
	<Message severity="INFO" prefix="[XFORM 203-101]" key="XFORM_PARTITION_STATUS_116" tag="" content="Partitioning array &apos;xtile.V.vec&apos; (matvec.cpp:3) in dimension 1 completely."/>
	<Message severity="INFO" prefix="[XFORM 203-721]" key="XFORM_LOOP_STREAM_STATUS_307" tag="" content="Change variable &apos;A&apos; to FIFO automatically."/>
	<Message severity="INFO" prefix="[XFORM 203-721]" key="XFORM_LOOP_STREAM_STATUS_309" tag="" content="Changing loop &apos;Loop_1_proc&apos; (matvec.cpp:8) to a process function for dataflow in function &apos;tiled_matvec&apos;."/>
	<Message severity="INFO" prefix="[XFORM 203-721]" key="XFORM_LOOP_STREAM_STATUS_309" tag="" content="Changing loop &apos;Loop_5_proc&apos; (matvec.cpp:33) to a process function for dataflow in function &apos;tiled_matvec&apos;."/>
	<Message severity="WARNING" prefix="[XFORM 203-713]" key="XFORM_DATAFLOW_WARNING_193" tag="ARRAY,SDX_ARRAY,DATAFLOW" content="All the elements of global array &apos;y&apos; should be updated in process function &apos;Loop_memset_y_proc&apos;, otherwise it may not be synthesized correctly."/>
	<Message severity="WARNING" prefix="[XFORM 203-713]" key="XFORM_DATAFLOW_WARNING_190" tag="SDX_CHANNEL,DATAFLOW" content="Reading dataflow channel &apos;ypartial&apos; in the middle of dataflow may stall the dataflow pipeline:"/>
	<Message severity="WARNING" prefix="[XFORM 203-713]" key="XFORM_DATAFLOW_WARNING_618" tag="SDX,DATAFLOW" content="Argument &apos;ypartial&apos; has read and write operations in process function &apos;Loop_5_proc&apos;."/>
	<Message severity="WARNING" prefix="[XFORM 203-713]" key="XFORM_DATAFLOW_WARNING_193" tag="ARRAY,SDX_ARRAY,DATAFLOW" content="All the elements of global array &apos;ypartial&apos; should be updated in process function &apos;Loop_5_proc&apos;, otherwise it may not be synthesized correctly."/>
	<Message severity="INFO" prefix="[XFORM 203-712]" key="XFORM_DATAFLOW_TRANSFORM_230" tag="DATAFLOW" content="Applying dataflow to function &apos;tiled_matvec&apos;, detected/extracted 5 process function(s): 
	 &apos;tiled_matvec.entry12&apos;
	 &apos;Loop_1_proc10&apos;
	 &apos;Block_tiled_matvec_.exit2_proc11&apos;
	 &apos;Loop_memset_y_proc&apos;
	 &apos;Loop_5_proc&apos;."/>
	<Message severity="INFO" prefix="[HLS 200-111]" key="HLS_111_965" tag="" content="Finished Pre-synthesis Time (s): cpu = 00:00:10 ; elapsed = 00:00:11 . Memory (MB): peak = 898.758 ; gain = 459.035 ; free physical = 163 ; free virtual = 2809"/>
	<Message severity="INFO" prefix="[XFORM 203-541]" key="XFORM_LOOPFLAT_STATUS_218" tag="" content="Flattening a loop nest &apos;Loop-2&apos; (matvec.cpp:26:15) in function &apos;Loop_memset_y_proc&apos;."/>
	<Message severity="WARNING" prefix="[XFORM 203-542]" key="XFORM_LOOPFLAT_INVALID_219" tag="LOOP,SDX_LOOP" content="Cannot flatten a loop nest &apos;Loop-1&apos; (matvec.cpp:8:15) in function &apos;Loop_1_proc10&apos; : 

the outer loop is not a perfect loop."/>
	<Message severity="WARNING" prefix="[XFORM 203-631]" key="XFORM_FRN_STATUS_336" tag="" content="Renaming function &apos;Block_tiled_matvec_.exit2_proc11&apos; to &apos;Block_tiled_matvec_.&apos; (matvec.cpp:3:52)"/>
	<Message severity="INFO" prefix="[HLS 200-472]" key="HLS 200-472" tag="" content="Inferring partial write operation for &apos;y&apos; (matvec.cpp:25:29)"/>
	<Message severity="INFO" prefix="[HLS 200-472]" key="HLS 200-472" tag="" content="Inferring partial write operation for &apos;y&apos; (matvec.cpp:28:4)"/>
	<Message severity="INFO" prefix="[HLS 200-472]" key="HLS 200-472" tag="" content="Inferring partial write operation for &apos;x&apos; (matvec.cpp:20:4)"/>
	<Message severity="INFO" prefix="[HLS 200-111]" key="HLS_111_965" tag="" content="Finished Architecture Synthesis Time (s): cpu = 00:00:11 ; elapsed = 00:00:11 . Memory (MB): peak = 962.758 ; gain = 523.035 ; free physical = 133 ; free virtual = 2758"/>
	<Message severity="INFO" prefix="[HLS 200-10]" key="HLS_10_1317" tag="" content="Starting hardware synthesis ..."/>
	<Message severity="INFO" prefix="[HLS 200-10]" key="HLS_10_1385" tag="" content="Synthesizing &apos;tiled_matvec&apos; ..."/>
	<Message severity="WARNING" prefix="[SYN 201-103]" key="SYN_MODULE_NAME_ILLEGAL_445" tag="" content="Legalizing function name &apos;tiled_matvec.entry3&apos; to &apos;tiled_matvec_entry3&apos;."/>
	<Message severity="WARNING" prefix="[SYN 201-103]" key="SYN_MODULE_NAME_ILLEGAL_445" tag="" content="Legalizing function name &apos;tiled_matvec.entry12&apos; to &apos;tiled_matvec_entry12&apos;."/>
	<Message severity="WARNING" prefix="[SYN 201-103]" key="SYN_MODULE_NAME_ILLEGAL_445" tag="" content="Legalizing function name &apos;Block_tiled_matvec_.&apos; to &apos;Block_tiled_matvec_s&apos;."/>
	<Message severity="INFO" prefix="[HLS 200-10]" key="HLS_10_1477" tag="" content="----------------------------------------------------------------"/>
	<Message severity="INFO" prefix="[HLS 200-42]" key="HLS_42_1438" tag="" content="-- Implementing module &apos;tiled_matvec_entry3&apos;"/>
	<Message severity="INFO" prefix="[HLS 200-10]" key="HLS_10_1478" tag="" content="----------------------------------------------------------------"/>
	<Message severity="INFO" prefix="[SCHED 204-11]" key="SCHED_SCHED_STATUS_597" tag="" content="Starting scheduling ..."/>
	<Message severity="INFO" prefix="[SCHED 204-11]" key="SCHED_SCHED_STATUS_596" tag="" content="Finished scheduling."/>
	<Message severity="INFO" prefix="[HLS 200-111]" key="HLS_111_966" tag="" content=" Elapsed time: 11.34 seconds; current allocated memory: 171.577 MB."/>
	<Message severity="INFO" prefix="[BIND 205-100]" key="BIND_100_926" tag="" content="Starting micro-architecture generation ..."/>
	<Message severity="INFO" prefix="[BIND 205-101]" key="BIND_101_698" tag="" content="Performing variable lifetime analysis."/>
	<Message severity="INFO" prefix="[BIND 205-101]" key="BIND_101_697" tag="" content="Exploring resource sharing."/>
	<Message severity="INFO" prefix="[BIND 205-101]" key="BIND_101_693" tag="" content="Binding ..."/>
	<Message severity="INFO" prefix="[BIND 205-100]" key="BIND_100_925" tag="" content="Finished micro-architecture generation."/>
	<Message severity="INFO" prefix="[HLS 200-111]" key="HLS_111_966" tag="" content=" Elapsed time: 0.01 seconds; current allocated memory: 171.626 MB."/>
	<Message severity="INFO" prefix="[HLS 200-10]" key="HLS_10_1477" tag="" content="----------------------------------------------------------------"/>
	<Message severity="INFO" prefix="[HLS 200-42]" key="HLS_42_1438" tag="" content="-- Implementing module &apos;tiled_matvec_entry12&apos;"/>
	<Message severity="INFO" prefix="[HLS 200-10]" key="HLS_10_1478" tag="" content="----------------------------------------------------------------"/>
	<Message severity="INFO" prefix="[SCHED 204-11]" key="SCHED_SCHED_STATUS_597" tag="" content="Starting scheduling ..."/>
	<Message severity="INFO" prefix="[SCHED 204-11]" key="SCHED_SCHED_STATUS_596" tag="" content="Finished scheduling."/>
	<Message severity="INFO" prefix="[HLS 200-111]" key="HLS_111_966" tag="" content=" Elapsed time: 0.05 seconds; current allocated memory: 171.744 MB."/>
	<Message severity="INFO" prefix="[BIND 205-100]" key="BIND_100_926" tag="" content="Starting micro-architecture generation ..."/>
	<Message severity="INFO" prefix="[BIND 205-101]" key="BIND_101_698" tag="" content="Performing variable lifetime analysis."/>
	<Message severity="INFO" prefix="[BIND 205-101]" key="BIND_101_697" tag="" content="Exploring resource sharing."/>
	<Message severity="INFO" prefix="[BIND 205-101]" key="BIND_101_693" tag="" content="Binding ..."/>
	<Message severity="INFO" prefix="[BIND 205-100]" key="BIND_100_925" tag="" content="Finished micro-architecture generation."/>
	<Message severity="INFO" prefix="[HLS 200-111]" key="HLS_111_966" tag="" content=" Elapsed time: 0 seconds; current allocated memory: 171.798 MB."/>
	<Message severity="INFO" prefix="[HLS 200-10]" key="HLS_10_1477" tag="" content="----------------------------------------------------------------"/>
	<Message severity="INFO" prefix="[HLS 200-42]" key="HLS_42_1438" tag="" content="-- Implementing module &apos;Loop_1_proc10&apos;"/>
	<Message severity="INFO" prefix="[HLS 200-10]" key="HLS_10_1478" tag="" content="----------------------------------------------------------------"/>
	<Message severity="INFO" prefix="[SCHED 204-11]" key="SCHED_SCHED_STATUS_597" tag="" content="Starting scheduling ..."/>
	<Message severity="INFO" prefix="[SCHED 204-61]" key="SCHED_PIPELINING_STATUS_41" tag="" content="Pipelining loop &apos;tiled_matvec_loadA&apos;."/>
	<Message severity="INFO" prefix="[SCHED 204-61]" key="SCHED_PIPELINING_STATUS_44" tag="" content="Pipelining result : Target II = 1, Final II = 1, Depth = 2."/>
	<Message severity="INFO" prefix="[SCHED 204-11]" key="SCHED_SCHED_STATUS_596" tag="" content="Finished scheduling."/>
	<Message severity="INFO" prefix="[HLS 200-111]" key="HLS_111_966" tag="" content=" Elapsed time: 0.06 seconds; current allocated memory: 171.911 MB."/>
	<Message severity="INFO" prefix="[BIND 205-100]" key="BIND_100_926" tag="" content="Starting micro-architecture generation ..."/>
	<Message severity="INFO" prefix="[BIND 205-101]" key="BIND_101_698" tag="" content="Performing variable lifetime analysis."/>
	<Message severity="INFO" prefix="[BIND 205-101]" key="BIND_101_697" tag="" content="Exploring resource sharing."/>
	<Message severity="INFO" prefix="[BIND 205-101]" key="BIND_101_693" tag="" content="Binding ..."/>
	<Message severity="INFO" prefix="[BIND 205-100]" key="BIND_100_925" tag="" content="Finished micro-architecture generation."/>
	<Message severity="INFO" prefix="[HLS 200-111]" key="HLS_111_966" tag="" content=" Elapsed time: 0.02 seconds; current allocated memory: 172.077 MB."/>
	<Message severity="INFO" prefix="[HLS 200-10]" key="HLS_10_1477" tag="" content="----------------------------------------------------------------"/>
	<Message severity="INFO" prefix="[HLS 200-42]" key="HLS_42_1438" tag="" content="-- Implementing module &apos;Block_tiled_matvec_s&apos;"/>
	<Message severity="INFO" prefix="[HLS 200-10]" key="HLS_10_1478" tag="" content="----------------------------------------------------------------"/>
	<Message severity="INFO" prefix="[SCHED 204-11]" key="SCHED_SCHED_STATUS_597" tag="" content="Starting scheduling ..."/>
	<Message severity="INFO" prefix="[SCHED 204-61]" key="SCHED_PIPELINING_STATUS_41" tag="" content="Pipelining loop &apos;tiled_matvec_loadx&apos;."/>
	<Message severity="INFO" prefix="[SCHED 204-61]" key="SCHED_PIPELINING_STATUS_44" tag="" content="Pipelining result : Target II = 1, Final II = 1, Depth = 1."/>
	<Message severity="INFO" prefix="[SCHED 204-11]" key="SCHED_SCHED_STATUS_596" tag="" content="Finished scheduling."/>
	<Message severity="INFO" prefix="[HLS 200-111]" key="HLS_111_966" tag="" content=" Elapsed time: 0.09 seconds; current allocated memory: 172.233 MB."/>
	<Message severity="INFO" prefix="[BIND 205-100]" key="BIND_100_926" tag="" content="Starting micro-architecture generation ..."/>
	<Message severity="INFO" prefix="[BIND 205-101]" key="BIND_101_698" tag="" content="Performing variable lifetime analysis."/>
	<Message severity="INFO" prefix="[BIND 205-101]" key="BIND_101_697" tag="" content="Exploring resource sharing."/>
	<Message severity="INFO" prefix="[BIND 205-101]" key="BIND_101_693" tag="" content="Binding ..."/>
	<Message severity="INFO" prefix="[BIND 205-100]" key="BIND_100_925" tag="" content="Finished micro-architecture generation."/>
	<Message severity="INFO" prefix="[HLS 200-111]" key="HLS_111_966" tag="" content=" Elapsed time: 0.02 seconds; current allocated memory: 172.377 MB."/>
	<Message severity="INFO" prefix="[HLS 200-10]" key="HLS_10_1477" tag="" content="----------------------------------------------------------------"/>
	<Message severity="INFO" prefix="[HLS 200-42]" key="HLS_42_1438" tag="" content="-- Implementing module &apos;Loop_memset_y_proc&apos;"/>
	<Message severity="INFO" prefix="[HLS 200-10]" key="HLS_10_1478" tag="" content="----------------------------------------------------------------"/>
	<Message severity="INFO" prefix="[SCHED 204-11]" key="SCHED_SCHED_STATUS_597" tag="" content="Starting scheduling ..."/>
	<Message severity="INFO" prefix="[SCHED 204-61]" key="SCHED_PIPELINING_STATUS_41" tag="" content="Pipelining loop &apos;L_tiled_matvec_compute&apos;."/>
	<Message severity="WARNING" prefix="[SCHED 204-68]" key="SCHED_CARRIED_CONSTRAINT_NOT_MET_32" tag="LOOP,SDX_LOOP,SCHEDULE" content="The II Violation in module &apos;Loop_memset_y_proc&apos; (Loop: L_tiled_matvec_compute): Unable to enforce a carried dependence constraint (II = 1, distance = 1, offset = 1)
   between &apos;store&apos; operation (&apos;y_addr_1_write_ln28&apos;, matvec.cpp:28) of variable &apos;add_ln28&apos;, matvec.cpp:28 on array &apos;y&apos; and &apos;load&apos; operation (&apos;y_load&apos;, matvec.cpp:28) on array &apos;y&apos;."/>
	<Message severity="INFO" prefix="[SCHED 204-61]" key="SCHED_PIPELINING_STATUS_44" tag="" content="Pipelining result : Target II = 1, Final II = 2, Depth = 4."/>
	<Message severity="INFO" prefix="[SCHED 204-11]" key="SCHED_SCHED_STATUS_596" tag="" content="Finished scheduling."/>
	<Message severity="INFO" prefix="[HLS 200-111]" key="HLS_111_966" tag="" content=" Elapsed time: 0.06 seconds; current allocated memory: 172.657 MB."/>
	<Message severity="INFO" prefix="[BIND 205-100]" key="BIND_100_926" tag="" content="Starting micro-architecture generation ..."/>
	<Message severity="INFO" prefix="[BIND 205-101]" key="BIND_101_698" tag="" content="Performing variable lifetime analysis."/>
	<Message severity="INFO" prefix="[BIND 205-101]" key="BIND_101_697" tag="" content="Exploring resource sharing."/>
	<Message severity="INFO" prefix="[BIND 205-101]" key="BIND_101_693" tag="" content="Binding ..."/>
	<Message severity="INFO" prefix="[BIND 205-100]" key="BIND_100_925" tag="" content="Finished micro-architecture generation."/>
	<Message severity="INFO" prefix="[HLS 200-111]" key="HLS_111_966" tag="" content=" Elapsed time: 0.03 seconds; current allocated memory: 172.884 MB."/>
	<Message severity="INFO" prefix="[HLS 200-10]" key="HLS_10_1477" tag="" content="----------------------------------------------------------------"/>
	<Message severity="INFO" prefix="[HLS 200-42]" key="HLS_42_1438" tag="" content="-- Implementing module &apos;Loop_5_proc&apos;"/>
	<Message severity="INFO" prefix="[HLS 200-10]" key="HLS_10_1478" tag="" content="----------------------------------------------------------------"/>
	<Message severity="INFO" prefix="[SCHED 204-11]" key="SCHED_SCHED_STATUS_597" tag="" content="Starting scheduling ..."/>
	<Message severity="INFO" prefix="[SCHED 204-11]" key="SCHED_SCHED_STATUS_596" tag="" content="Finished scheduling."/>
	<Message severity="INFO" prefix="[HLS 200-111]" key="HLS_111_966" tag="" content=" Elapsed time: 0.06 seconds; current allocated memory: 172.973 MB."/>
	<Message severity="INFO" prefix="[BIND 205-100]" key="BIND_100_926" tag="" content="Starting micro-architecture generation ..."/>
	<Message severity="INFO" prefix="[BIND 205-101]" key="BIND_101_698" tag="" content="Performing variable lifetime analysis."/>
	<Message severity="INFO" prefix="[BIND 205-101]" key="BIND_101_697" tag="" content="Exploring resource sharing."/>
	<Message severity="INFO" prefix="[BIND 205-101]" key="BIND_101_693" tag="" content="Binding ..."/>
	<Message severity="INFO" prefix="[BIND 205-100]" key="BIND_100_925" tag="" content="Finished micro-architecture generation."/>
	<Message severity="INFO" prefix="[HLS 200-111]" key="HLS_111_966" tag="" content=" Elapsed time: 0.01 seconds; current allocated memory: 173.071 MB."/>
	<Message severity="INFO" prefix="[HLS 200-10]" key="HLS_10_1477" tag="" content="----------------------------------------------------------------"/>
	<Message severity="INFO" prefix="[HLS 200-42]" key="HLS_42_1438" tag="" content="-- Implementing module &apos;tiled_matvec&apos;"/>
	<Message severity="INFO" prefix="[HLS 200-10]" key="HLS_10_1478" tag="" content="----------------------------------------------------------------"/>
	<Message severity="INFO" prefix="[SCHED 204-11]" key="SCHED_SCHED_STATUS_597" tag="" content="Starting scheduling ..."/>
	<Message severity="INFO" prefix="[SCHED 204-11]" key="SCHED_SCHED_STATUS_596" tag="" content="Finished scheduling."/>
	<Message severity="INFO" prefix="[HLS 200-111]" key="HLS_111_966" tag="" content=" Elapsed time: 0.03 seconds; current allocated memory: 173.226 MB."/>
	<Message severity="INFO" prefix="[BIND 205-100]" key="BIND_100_926" tag="" content="Starting micro-architecture generation ..."/>
	<Message severity="INFO" prefix="[BIND 205-101]" key="BIND_101_698" tag="" content="Performing variable lifetime analysis."/>
	<Message severity="INFO" prefix="[BIND 205-101]" key="BIND_101_697" tag="" content="Exploring resource sharing."/>
	<Message severity="INFO" prefix="[BIND 205-101]" key="BIND_101_693" tag="" content="Binding ..."/>
	<Message severity="INFO" prefix="[BIND 205-100]" key="BIND_100_925" tag="" content="Finished micro-architecture generation."/>
	<Message severity="INFO" prefix="[HLS 200-111]" key="HLS_111_966" tag="" content=" Elapsed time: 0.06 seconds; current allocated memory: 173.398 MB."/>
	<Message severity="INFO" prefix="[HLS 200-10]" key="HLS_10_1483" tag="" content="----------------------------------------------------------------"/>
	<Message severity="INFO" prefix="[HLS 200-10]" key="HLS_10_1484" tag="" content="-- Generating RTL for module &apos;tiled_matvec_entry3&apos;"/>
	<Message severity="INFO" prefix="[HLS 200-10]" key="HLS_10_1485" tag="" content="----------------------------------------------------------------"/>
	<Message severity="INFO" prefix="[RTGEN 206-100]" key="RTGEN_100_856" tag="" content="Finished creating RTL model for &apos;tiled_matvec_entry3&apos;."/>
	<Message severity="INFO" prefix="[HLS 200-111]" key="HLS_111_966" tag="" content=" Elapsed time: 0.04 seconds; current allocated memory: 173.568 MB."/>
	<Message severity="INFO" prefix="[HLS 200-10]" key="HLS_10_1483" tag="" content="----------------------------------------------------------------"/>
	<Message severity="INFO" prefix="[HLS 200-10]" key="HLS_10_1484" tag="" content="-- Generating RTL for module &apos;tiled_matvec_entry12&apos;"/>
	<Message severity="INFO" prefix="[HLS 200-10]" key="HLS_10_1485" tag="" content="----------------------------------------------------------------"/>
	<Message severity="INFO" prefix="[RTGEN 206-100]" key="RTGEN_100_856" tag="" content="Finished creating RTL model for &apos;tiled_matvec_entry12&apos;."/>
	<Message severity="INFO" prefix="[HLS 200-111]" key="HLS_111_966" tag="" content=" Elapsed time: 0.02 seconds; current allocated memory: 173.850 MB."/>
	<Message severity="INFO" prefix="[HLS 200-10]" key="HLS_10_1483" tag="" content="----------------------------------------------------------------"/>
	<Message severity="INFO" prefix="[HLS 200-10]" key="HLS_10_1484" tag="" content="-- Generating RTL for module &apos;Loop_1_proc10&apos;"/>
	<Message severity="INFO" prefix="[HLS 200-10]" key="HLS_10_1485" tag="" content="----------------------------------------------------------------"/>
	<Message severity="INFO" prefix="[RTGEN 206-100]" key="RTGEN_100_856" tag="" content="Finished creating RTL model for &apos;Loop_1_proc10&apos;."/>
	<Message severity="INFO" prefix="[HLS 200-111]" key="HLS_111_966" tag="" content=" Elapsed time: 0.03 seconds; current allocated memory: 174.270 MB."/>
	<Message severity="INFO" prefix="[HLS 200-10]" key="HLS_10_1483" tag="" content="----------------------------------------------------------------"/>
	<Message severity="INFO" prefix="[HLS 200-10]" key="HLS_10_1484" tag="" content="-- Generating RTL for module &apos;Block_tiled_matvec_s&apos;"/>
	<Message severity="INFO" prefix="[HLS 200-10]" key="HLS_10_1485" tag="" content="----------------------------------------------------------------"/>
	<Message severity="INFO" prefix="[RTGEN 206-100]" key="RTGEN_100_856" tag="" content="Finished creating RTL model for &apos;Block_tiled_matvec_s&apos;."/>
	<Message severity="INFO" prefix="[HLS 200-111]" key="HLS_111_966" tag="" content=" Elapsed time: 0.07 seconds; current allocated memory: 174.980 MB."/>
	<Message severity="INFO" prefix="[HLS 200-10]" key="HLS_10_1483" tag="" content="----------------------------------------------------------------"/>
	<Message severity="INFO" prefix="[HLS 200-10]" key="HLS_10_1484" tag="" content="-- Generating RTL for module &apos;Loop_memset_y_proc&apos;"/>
	<Message severity="INFO" prefix="[HLS 200-10]" key="HLS_10_1485" tag="" content="----------------------------------------------------------------"/>
	<Message severity="INFO" prefix="[RTGEN 206-100]" key="RTGEN_100_856" tag="" content="Finished creating RTL model for &apos;Loop_memset_y_proc&apos;."/>
	<Message severity="INFO" prefix="[HLS 200-111]" key="HLS_111_966" tag="" content=" Elapsed time: 0.05 seconds; current allocated memory: 175.799 MB."/>
	<Message severity="INFO" prefix="[HLS 200-10]" key="HLS_10_1483" tag="" content="----------------------------------------------------------------"/>
	<Message severity="INFO" prefix="[HLS 200-10]" key="HLS_10_1484" tag="" content="-- Generating RTL for module &apos;Loop_5_proc&apos;"/>
	<Message severity="INFO" prefix="[HLS 200-10]" key="HLS_10_1485" tag="" content="----------------------------------------------------------------"/>
	<Message severity="INFO" prefix="[RTGEN 206-100]" key="RTGEN_100_856" tag="" content="Finished creating RTL model for &apos;Loop_5_proc&apos;."/>
	<Message severity="INFO" prefix="[HLS 200-111]" key="HLS_111_966" tag="" content=" Elapsed time: 0.1 seconds; current allocated memory: 176.768 MB."/>
	<Message severity="INFO" prefix="[HLS 200-10]" key="HLS_10_1483" tag="" content="----------------------------------------------------------------"/>
	<Message severity="INFO" prefix="[HLS 200-10]" key="HLS_10_1484" tag="" content="-- Generating RTL for module &apos;tiled_matvec&apos;"/>
	<Message severity="INFO" prefix="[HLS 200-10]" key="HLS_10_1485" tag="" content="----------------------------------------------------------------"/>
	<Message severity="INFO" prefix="[RTGEN 206-500]" key="PREPROC_IO_COMP_CONFLICT_1950" tag="" content="Setting interface mode on port &apos;tiled_matvec/Atile_V_vec_0&apos; to &apos;ap_fifo&apos;."/>
	<Message severity="INFO" prefix="[RTGEN 206-500]" key="PREPROC_IO_COMP_CONFLICT_1950" tag="" content="Setting interface mode on port &apos;tiled_matvec/Atile_V_vec_1&apos; to &apos;ap_fifo&apos;."/>
	<Message severity="INFO" prefix="[RTGEN 206-500]" key="PREPROC_IO_COMP_CONFLICT_1950" tag="" content="Setting interface mode on port &apos;tiled_matvec/xtile_V_vec_0&apos; to &apos;ap_fifo&apos;."/>
	<Message severity="INFO" prefix="[RTGEN 206-500]" key="PREPROC_IO_COMP_CONFLICT_1950" tag="" content="Setting interface mode on port &apos;tiled_matvec/xtile_V_vec_1&apos; to &apos;ap_fifo&apos;."/>
	<Message severity="INFO" prefix="[RTGEN 206-500]" key="PREPROC_IO_COMP_CONFLICT_1950" tag="" content="Setting interface mode on port &apos;tiled_matvec/ypartial&apos; to &apos;ap_memory&apos;."/>
	<Message severity="INFO" prefix="[RTGEN 206-500]" key="PREPROC_IO_COMP_CONFLICT_1950" tag="" content="Setting interface mode on port &apos;tiled_matvec/i1&apos; to &apos;ap_none&apos;."/>
	<Message severity="INFO" prefix="[RTGEN 206-500]" key="PREPROC_IO_COMP_CONFLICT_1950" tag="" content="Setting interface mode on port &apos;tiled_matvec/i2&apos; to &apos;ap_none&apos;."/>
	<Message severity="INFO" prefix="[RTGEN 206-500]" key="PREPROC_IO_COMP_CONFLICT_1950" tag="" content="Setting interface mode on function &apos;tiled_matvec&apos; to &apos;ap_ctrl_hs&apos;."/>
	<Message severity="INFO" prefix="[SYN 201-210]" key="SYN_210_889" tag="" content="Renamed object name &apos;start_for_tiled_matvec_entry12_U0&apos; to &apos;start_for_tiled_mbkb&apos; due to the length limit 20"/>
	<Message severity="WARNING" prefix="[RTGEN 206-101]" key="RTGEN_101_738" tag="" content="Port &apos;tiled_matvec/i1&apos; has no fanin or fanout and is left dangling.
               Please use C simulation to confirm this function argument can be read from or written to."/>
	<Message severity="INFO" prefix="[RTGEN 206-100]" key="RTGEN_100_856" tag="" content="Finished creating RTL model for &apos;tiled_matvec&apos;."/>
	<Message severity="INFO" prefix="[HLS 200-111]" key="HLS_111_966" tag="" content=" Elapsed time: 0.07 seconds; current allocated memory: 177.873 MB."/>
	<Message severity="INFO" prefix="[HLS 200-790]" key="HLS 200-790" tag="LOOP,SDX_LOOP" content="**** Loop Constraint Status: All loop constraints were NOT satisfied."/>
	<Message severity="INFO" prefix="[HLS 200-789]" key="HLS 200-789" tag="THROUGHPUT,SDX_KERNEL" content="**** Estimated Fmax: 151.29 MHz"/>
	<Message severity="INFO" prefix="[HLS 200-741]" key="HLS 200-741" tag="" content="Implementing PIPO tiled_matvec_y_memcore using a single memory for all blocks"/>
	<Message severity="INFO" prefix="[RTMG 210-278]" key="RTMG_278_1790" tag="" content="Implementing memory &apos;tiled_matvec_y_memcore_ram (RAM)&apos; using distributed RAMs."/>
	<Message severity="INFO" prefix="[HLS 200-741]" key="HLS 200-741" tag="" content="Implementing PIPO tiled_matvec_x_memcore using a single memory for all blocks"/>
	<Message severity="INFO" prefix="[RTMG 210-278]" key="RTMG_278_1792" tag="" content="Implementing memory &apos;tiled_matvec_x_memcore_ram (RAM)&apos; using distributed RAMs with power-on initialization."/>
	<Message severity="INFO" prefix="[RTMG 210-285]" key="RTMG_285_1799" tag="" content="Implementing FIFO &apos;i2_c1_U(fifo_w32_d2_A)&apos; using Shift Registers."/>
	<Message severity="INFO" prefix="[RTMG 210-285]" key="RTMG_285_1799" tag="" content="Implementing FIFO &apos;i2_c_U(fifo_w32_d2_A)&apos; using Shift Registers."/>
	<Message severity="INFO" prefix="[RTMG 210-285]" key="RTMG_285_1799" tag="" content="Implementing FIFO &apos;A_U(fifo_w32_d4_A)&apos; using Shift Registers."/>
	<Message severity="INFO" prefix="[RTMG 210-285]" key="RTMG_285_1799" tag="" content="Implementing FIFO &apos;i2_load_loc_c_U(fifo_w32_d3_A)&apos; using Shift Registers."/>
	<Message severity="INFO" prefix="[RTMG 210-285]" key="RTMG_285_1799" tag="" content="Implementing FIFO &apos;start_for_tiled_mbkb_U(start_for_tiled_mbkb)&apos; using Shift Registers."/>
	<Message severity="INFO" prefix="[HLS 200-741]" key="HLS 200-741" tag="" content="Implementing PIPO tiled_matvec_y_memcore using a single memory for all blocks"/>
	<Message severity="INFO" prefix="[HLS 200-741]" key="HLS 200-741" tag="" content="Implementing PIPO tiled_matvec_x_memcore using a single memory for all blocks"/>
	<Message severity="INFO" prefix="[HLS 200-741]" key="HLS 200-741" tag="" content="Implementing PIPO tiled_matvec_y_memcore using a single memory for all blocks"/>
	<Message severity="INFO" prefix="[HLS 200-741]" key="HLS 200-741" tag="" content="Implementing PIPO tiled_matvec_x_memcore using a single memory for all blocks"/>
	<Message severity="INFO" prefix="[HLS 200-111]" key="HLS_111_965" tag="" content="Finished generating all RTL models Time (s): cpu = 00:00:13 ; elapsed = 00:00:14 . Memory (MB): peak = 962.758 ; gain = 523.035 ; free physical = 139 ; free virtual = 2700"/>
	<Message severity="INFO" prefix="[VHDL 208-304]" key="VHDL_304_1066" tag="" content="Generating VHDL RTL for tiled_matvec."/>
	<Message severity="INFO" prefix="[VLOG 209-307]" key="VLOG_307_1067" tag="" content="Generating Verilog RTL for tiled_matvec."/>
</Messages>
